multiagent_core/__init__.py
multiagent_core/__main__.py
multiagent_core/_template_build.py
multiagent_core/_template_sync.py
multiagent_core/cli.py
multiagent_core/config.py
multiagent_core/init_progress.py
multiagent_core/legacy_init.py
multiagent_core/templates/mcp-servers-registry.json
multiagent_core/templates/agent-configs/CLAUDE.md
multiagent_core/templates/agent-configs/CODEX.md
multiagent_core/templates/agent-configs/COPILOT.md
multiagent_core/templates/agent-configs/GEMINI.md
multiagent_core/templates/agent-configs/QWEN.md
multiagent_core/utils/__init__.py
multiagent_core/utils/version_detection.py
multiagent_core-4.6.0.dist-info/METADATA
multiagent_core-4.6.0.dist-info/WHEEL
multiagent_core-4.6.0.dist-info/entry_points.txt
multiagent_core-4.6.0.dist-info/top_level.txt
multiagent_core-4.6.0.dist-info/RECORD
