Metadata-Version: 2.4
Name: multiagent-core
Version: 4.6.0
Summary: Foundation framework with intelligent directory management for multi-agent development
License-Expression: MIT
Project-URL: Homepage, https://github.com/vanman2024/multiagent-core
Project-URL: Issues, https://github.com/vanman2024/multiagent-core/issues
Classifier: Development Status :: 4 - Beta
Classifier: Intended Audience :: Developers
Classifier: Programming Language :: Python :: 3
Classifier: Programming Language :: Python :: 3.8
Classifier: Programming Language :: Python :: 3.9
Classifier: Programming Language :: Python :: 3.10
Classifier: Programming Language :: Python :: 3.11
Classifier: Programming Language :: Python :: 3.12
Requires-Python: >=3.8
Requires-Dist: click>=8.0.0
Requires-Dist: fastapi>=0.111.0
Requires-Dist: httpx>=0.24.0
Requires-Dist: importlib-resources>=5.0.0
Requires-Dist: packaging>=23.0
Requires-Dist: psutil>=5.9.0
Requires-Dist: pydantic>=2.6.0
Requires-Dist: pyyaml>=6.0
Requires-Dist: requests>=2.25.0
Requires-Dist: rich>=10.0.0
Requires-Dist: setuptools>=61.0
